{
  "project_info": {
    "project_number": "473882501204",
    "project_id": "qqbot-50a1c",
    "storage_bucket": "qqbot-50a1c.appspot.com"
  },
  "client": [
    {
      "client_info": {
        "mobilesdk_app_id": "1:473882501204:android:15167b78c0f90b61908dc1",
        "android_client_info": {
          "package_name": "com.yunshen.yunapp"
        }
      },
      "oauth_client": [],
      "api_key": [
        {
          "current_key": "AIzaSyCym3_1W2KaJ9ISNrgS31hHpod8T-uIg4A"
        }
      ],
      "services": {
        "appinvite_service": {
          "other_platform_oauth_client": []
        }
      }
    }
  ],
  "configuration_version": "1"
}